[{"district":"Wong Tai Sin","coordinate":[22.3416,114.1938],"locations":["Wong Tai Sin Area"]},{"district":"Kowloon City","coordinate":[22.3172,114.1876],"locations":["Hung Hom","Kowloon City","Kowloon City Area","To Kwa Wan"]},{"district":"Kwun Tong","coordinate":[22.3121,114.2263],"locations":["Kowloon Bay","Kwun Tong","Kwun Tong Area","Ngau Tau Kok"]},{"district":"Sai Kung","coordinate":[22.3074,114.26],"locations":["Sai Kung","Sai Kung Area","Tseung Kwan O"]},{"district":"North","coordinate":[22.5012,114.1279],"locations":["Fanling","Northern NT Area","Sheung Shui"]},{"district":"Central-Western","coordinate":[22.2819,114.1582],"locations":["Admiralty","Central","Central & Western Area","Sai Wan","Sai Ying Pun","Sheung Wan"]},{"district":"Wan Chai","coordinate":[22.2775,114.1731],"locations":["Causeway Bay","Wan Chai","Wan Chai Area"]},{"district":"Eastern","coordinate":[22.2912,114.2005],"locations":["Chai Wan","Eastern Area","North Point","Quarry Bay","Sai Wan Ho","Shau Kei Wan","Tin Shui Wai","Tai Koo","Tin Hau"]},{"district":"Tuen Mun","coordinate":[22.3948,113.9731],"locations":["Tuen Mun Area"]},{"district":"Yuen Long","coordinate":[22.446,114.0347],"locations":["Tin Shui Wai","Yuen Long","Yuen Long Area"]},{"district":"Southern","coordinate":[22.2419,114.1561],"locations":["Aberdeen","Pok Fu Lam","Southern Area"]},{"district":"Islands","coordinate":[22.2892,113.9414],"locations":["Airport Area","Cheung Chau Area","Lantau Island","Tung Chung"]},{"district":"Sham Shui Po","coordinate":[22.3307,114.1622],"locations":["Cheung Sha Wan","Lai Chi Kok","Sham Shui Po","Sham Shui Po Area"]},{"district":"Yau Tsim Mong","coordinate":[22.3128,114.1706],"locations":["Mong Kok","Tsim Sha Tsui","Yau Ma Tei","Yau Tsim Mong Area"]},{"district":"Kwai Tsing","coordinate":[22.363,114.1312],"locations":["Kwai Fong","Kwai Hing","Kwai Tsing Area","Tsing Yi"]},{"district":"Tsuen Wan","coordinate":[22.3736,114.1177],"locations":["Tsuen Wan Area"]},{"district":"Tai Po","coordinate":[22.4445,114.1704],"locations":["Tai Po Area"]},{"district":"Sha Tin","coordinate":[22.3818,114.1869],"locations":["Shatin Area"]}]